mycalc/calculator.py
dhkimpypack01-0.0.2.dist-info/LICENSE
dhkimpypack01-0.0.2.dist-info/METADATA
dhkimpypack01-0.0.2.dist-info/WHEEL
dhkimpypack01-0.0.2.dist-info/top_level.txt
dhkimpypack01-0.0.2.dist-info/RECORD
