Metadata-Version: 2.1
Name: dhkimpypack01
Version: 0.0.2
Summary: 타 과목 확률과 통계 에서 주로 쓰이는 라이브러리를 모아놓은 패키지
Home-page: https://github.com/mong0411/mycalc
Download-URL: https://github.com/mong0411/mycalc/
Author: dhkim
Classifier: Programming Language :: Python :: 3
License-File: LICENSE
